idm/__init__.py
idm/idm.py
indomarek-1.3.dist-info/METADATA
indomarek-1.3.dist-info/WHEEL
indomarek-1.3.dist-info/entry_points.txt
indomarek-1.3.dist-info/top_level.txt
indomarek-1.3.dist-info/RECORD
