Metadata-Version: 2.1
Name: indomarek
Version: 1.3
Summary: hanya sebuah script biasa
Home-page: https://github.com/username/my_project
Author: robbi 13
Author-email: email@example.com
